{
    "feature_importances": {
        "threshold": {
            "importances_mean": [
                0.03474576271186436,
                0.031355932203389836,
                0.022881355932203418,
                0.0059322033898304705,
                0.02203389830508473,
                0.019491525423728784,
                0.03389830508474578,
                0.0008474576271186862,
                0.015254237288135575,
                0.0016949152542372614,
                0.0016949152542372614,
                0.0,
                0.0,
                0.0,
                0.0,
                0.0,
                0.0
            ],
            "importances_std": [
                0.0,
                0.0,
                0.0,
                0.0,
                0.0,
                0.0,
                0.0,
                0.0,
                0.0,
                0.0,
                0.0,
                0.0,
                0.0,
                0.0,
                0.0,
                0.0,
                0.0
            ],
            "importances": [
                [
                    0.03474576271186436
                ],
                [
                    0.031355932203389836
                ],
                [
                    0.022881355932203418
                ],
                [
                    0.0059322033898304705
                ],
                [
                    0.02203389830508473
                ],
                [
                    0.019491525423728784
                ],
                [
                    0.03389830508474578
                ],
                [
                    0.0008474576271186862
                ],
                [
                    0.015254237288135575
                ],
                [
                    0.0016949152542372614
                ],
                [
                    0.0016949152542372614
                ],
                [
                    0.0
                ],
                [
                    0.0
                ],
                [
                    0.0
                ],
                [
                    0.0
                ],
                [
                    0.0
                ],
                [
                    0.0
                ]
            ]
        },
        "distance": {
            "importances_mean": [
                0.03443099273607764,
                0.025835351089589453,
                0.019709443099272694,
                0.010193704600483855,
                0.017627118644068074,
                0.009007263922518605,
                0.018135593220338087,
                0.0007748184019372717,
                0.008087167070217172,
                0.0017917675544795175,
                0.0008232445520580667,
                0.00014527845036316211,
                9.685230024203406e-05,
                4.842615012090601e-05,
                0.0002663438256658157,
                7.263922518163657e-05,
                2.4213075060508515e-05
            ],
            "importances_std": [
                0.0,
                0.0,
                0.0,
                0.0,
                0.0,
                0.0,
                0.0,
                0.0,
                0.0,
                0.0,
                0.0,
                0.0,
                0.0,
                0.0,
                0.0,
                0.0,
                0.0
            ],
            "importances": [
                [
                    0.03443099273607764
                ],
                [
                    0.025835351089589453
                ],
                [
                    0.019709443099272694
                ],
                [
                    0.010193704600483855
                ],
                [
                    0.017627118644068074
                ],
                [
                    0.009007263922518605
                ],
                [
                    0.018135593220338087
                ],
                [
                    0.0007748184019372717
                ],
                [
                    0.008087167070217172
                ],
                [
                    0.0017917675544795175
                ],
                [
                    0.0008232445520580667
                ],
                [
                    0.00014527845036316211
                ],
                [
                    9.685230024203406e-05
                ],
                [
                    4.842615012090601e-05
                ],
                [
                    0.0002663438256658157
                ],
                [
                    7.263922518163657e-05
                ],
                [
                    2.4213075060508515e-05
                ]
            ]
        },
        "exact_accuracy": {
            "importances_mean": [
                0.18813559322033901,
                0.15508474576271192,
                0.19830508474576275,
                0.07288135593220346,
                0.0898305084745763,
                0.0754237288135593,
                0.07203389830508478,
                0.016949152542372947,
                0.04322033898305089,
                0.03220338983050852,
                0.007627118644067843,
                0.0025423728813559476,
                0.0016949152542372614,
                0.0,
                0.007627118644067843,
                0.0016949152542372614,
                0.0008474576271186862
            ],
            "importances_std": [
                0.0,
                0.0,
                0.0,
                0.0,
                0.0,
                0.0,
                0.0,
                0.0,
                0.0,
                0.0,
                0.0,
                0.0,
                0.0,
                0.0,
                0.0,
                0.0,
                0.0
            ],
            "importances": [
                [
                    0.18813559322033901
                ],
                [
                    0.15508474576271192
                ],
                [
                    0.19830508474576275
                ],
                [
                    0.07288135593220346
                ],
                [
                    0.0898305084745763
                ],
                [
                    0.0754237288135593
                ],
                [
                    0.07203389830508478
                ],
                [
                    0.016949152542372947
                ],
                [
                    0.04322033898305089
                ],
                [
                    0.03220338983050852
                ],
                [
                    0.007627118644067843
                ],
                [
                    0.0025423728813559476
                ],
                [
                    0.0016949152542372614
                ],
                [
                    0.0
                ],
                [
                    0.007627118644067843
                ],
                [
                    0.0016949152542372614
                ],
                [
                    0.0008474576271186862
                ]
            ]
        },
        "balanced_accuracy": {
            "importances_mean": [
                0.19876574347322157,
                0.23735602524748978,
                0.1693435302243691,
                0.06366719107033136,
                0.15265831282870035,
                0.1503654593345622,
                0.14358177827554836,
                0.014393711172402623,
                0.12120313828870832,
                0.025506405461017345,
                0.0064522695151687515,
                0.001987538595226268,
                0.0012202562538132788,
                -1.627008338411784e-05,
                0.0057973265294802845,
                0.0014356499713424897,
                0.000606060606060721
            ],
            "importances_std": [
                0.0,
                0.0,
                0.0,
                0.0,
                0.0,
                0.0,
                0.0,
                0.0,
                0.0,
                0.0,
                0.0,
                0.0,
                0.0,
                0.0,
                0.0,
                0.0,
                0.0
            ],
            "importances": [
                [
                    0.19876574347322157
                ],
                [
                    0.23735602524748978
                ],
                [
                    0.1693435302243691
                ],
                [
                    0.06366719107033136
                ],
                [
                    0.15265831282870035
                ],
                [
                    0.1503654593345622
                ],
                [
                    0.14358177827554836
                ],
                [
                    0.014393711172402623
                ],
                [
                    0.12120313828870832
                ],
                [
                    0.025506405461017345
                ],
                [
                    0.0064522695151687515
                ],
                [
                    0.001987538595226268
                ],
                [
                    0.0012202562538132788
                ],
                [
                    -1.627008338411784e-05
                ],
                [
                    0.0057973265294802845
                ],
                [
                    0.0014356499713424897
                ],
                [
                    0.000606060606060721
                ]
            ]
        }
    },
    "feature_names_in": [
        "Niveau s\u00e5rv\u00e6v",
        "S\u00e5rskorpe",
        "Granulationsv\u00e6v",
        "Epithelialisering",
        "Kontraktion",
        "Hyper\u00e6mi",
        "\u00d8dem",
        "Eksudat",
        "Infektionsniveau",
        "Eksudattype_0.0",
        "Eksudattype_1.0",
        "Eksudattype_2.0",
        "Eksudattype_3.0",
        "Eksudattype_4.0",
        "Eksudattype_5.0",
        "Eksudattype_6.0",
        "Eksudattype_7.0"
    ],
    "train_accuracies": {
        "threshold": 0.9576271186440678,
        "distance": 0.9695399515738472,
        "exact_accuracy": 0.6677966101694915,
        "balanced_accuracy": 0.6108345961900159
    },
    "train_precision": 0.6751932719853602,
    "train_recall": 0.6677966101694915,
    "test_accuracies": {
        "threshold": 0.9238410596026491,
        "distance": 0.9578051087984861,
        "exact_accuracy": 0.5794701986754967,
        "balanced_accuracy": 0.45490111297527563
    },
    "test_precision": 0.5821725783575897,
    "test_recall": 0.5794701986754967,
    "train_pred_y": [
        2,
        4,
        4,
        3,
        10,
        5,
        3,
        5,
        15,
        35,
        31,
        4,
        4,
        4,
        30,
        10,
        5,
        3,
        20,
        20,
        10,
        1,
        5,
        5,
        15,
        3,
        10,
        20,
        25,
        5,
        15,
        25,
        3,
        15,
        4,
        1,
        1,
        4,
        10,
        4,
        5,
        15,
        2,
        4,
        2,
        25,
        4,
        2,
        4,
        10,
        4,
        10,
        20,
        35,
        30,
        5,
        25,
        20,
        4,
        10,
        15,
        4,
        20,
        20,
        10,
        20,
        31,
        20,
        2,
        4,
        20,
        35,
        5,
        1,
        4,
        1,
        35,
        4,
        4,
        35,
        20,
        15,
        1,
        20,
        15,
        10,
        20,
        3,
        5,
        20,
        10,
        25,
        15,
        1,
        10,
        10,
        4,
        4,
        2,
        4,
        4,
        15,
        2,
        10,
        2,
        2,
        1,
        35,
        1,
        2,
        10,
        4,
        4,
        2,
        15,
        4,
        15,
        3,
        25,
        10,
        20,
        2,
        25,
        31,
        20,
        4,
        30,
        1,
        4,
        4,
        1,
        1,
        10,
        4,
        10,
        15,
        5,
        4,
        10,
        3,
        3,
        4,
        1,
        2,
        3,
        4,
        4,
        10,
        4,
        4,
        2,
        10,
        5,
        30,
        15,
        3,
        10,
        3,
        2,
        15,
        35,
        30,
        3,
        2,
        1,
        4,
        20,
        2,
        20,
        4,
        25,
        25,
        4,
        5,
        4,
        4,
        4,
        5,
        4,
        2,
        2,
        20,
        2,
        4,
        1,
        1,
        10,
        2,
        10,
        5,
        2,
        3,
        1,
        1,
        3,
        10,
        4,
        4,
        20,
        1,
        10,
        31,
        5,
        2,
        35,
        3,
        3,
        5,
        1,
        4,
        10,
        1,
        20,
        3,
        1,
        3,
        5,
        3,
        3,
        20,
        20,
        15,
        5,
        4,
        3,
        30,
        15,
        4,
        2,
        3,
        3,
        1,
        1,
        15,
        20,
        1,
        2,
        3,
        2,
        3,
        2,
        1,
        4,
        2,
        1,
        2,
        25,
        4,
        10,
        5,
        4,
        1,
        3,
        15,
        10,
        25,
        4,
        20,
        2,
        1,
        2,
        1,
        10,
        4,
        3,
        15,
        15,
        2,
        20,
        2,
        15,
        1,
        20,
        2,
        15,
        1,
        5,
        4,
        10,
        5,
        10,
        3,
        15,
        10,
        30,
        3,
        2,
        2,
        3,
        25,
        2,
        31,
        5,
        30,
        1,
        4,
        10,
        1,
        3,
        4,
        10,
        15,
        3,
        3,
        2,
        30,
        35,
        15,
        10,
        10,
        2,
        10,
        4,
        10,
        2,
        20,
        3,
        25,
        3,
        15,
        4,
        1,
        4,
        35,
        4,
        30,
        1,
        5,
        15,
        2,
        15,
        5,
        5,
        4,
        3,
        1,
        2,
        1,
        10,
        15,
        3,
        20,
        15,
        3,
        10,
        2,
        3,
        35,
        5,
        5,
        2,
        20,
        4,
        1,
        1,
        20,
        4,
        10,
        3,
        25,
        3,
        1,
        10,
        25,
        3,
        20,
        4,
        2,
        1,
        10,
        35,
        25,
        4,
        2,
        25,
        10,
        25,
        1,
        25,
        5,
        15,
        5,
        4,
        25,
        3,
        1,
        3,
        1,
        1,
        5,
        25,
        20,
        5,
        30,
        4,
        1,
        1,
        2,
        10,
        2,
        4,
        4,
        5,
        4,
        10,
        2,
        1,
        25,
        30,
        2,
        2,
        10,
        15,
        10,
        10,
        4,
        2,
        15,
        3,
        5,
        3,
        1,
        4,
        20,
        4,
        5,
        15,
        4,
        20,
        5,
        1,
        3,
        20,
        3,
        2,
        20,
        4,
        4,
        5,
        3,
        2,
        3,
        20,
        20,
        15,
        2,
        4,
        5,
        1,
        4,
        5,
        4,
        4,
        10,
        4,
        1,
        4,
        15,
        4,
        1,
        4,
        1,
        10,
        3,
        1,
        25,
        10,
        1,
        2,
        3,
        3,
        30,
        1,
        1,
        10,
        3,
        4,
        3,
        15,
        3,
        10,
        10,
        10,
        5,
        2,
        1,
        4,
        10,
        3,
        10,
        2,
        2,
        1,
        5,
        3,
        2,
        2,
        2,
        3,
        2,
        10,
        3,
        10,
        10,
        4,
        4,
        3,
        15,
        3,
        20,
        2,
        5,
        15,
        20,
        31,
        1,
        3,
        1,
        3,
        3,
        1,
        3,
        5,
        2,
        15,
        2,
        2,
        2,
        10,
        4,
        10,
        2,
        15,
        31,
        3,
        2,
        5,
        1,
        20,
        5,
        2,
        5,
        5,
        20,
        20,
        2,
        2,
        4,
        20,
        2,
        15,
        10,
        2,
        2,
        5,
        15,
        4,
        2,
        4,
        2,
        1,
        3,
        1,
        2,
        3,
        10,
        10,
        1,
        4,
        4,
        3,
        4,
        15,
        4,
        4,
        2,
        15,
        4,
        10,
        10,
        1,
        3,
        15,
        30,
        3,
        4,
        4,
        20,
        2,
        1,
        2,
        3,
        2,
        2,
        3,
        4,
        2,
        20,
        20,
        1,
        10,
        4,
        3,
        25,
        15,
        10,
        15,
        25,
        3,
        2,
        4,
        3,
        10,
        5,
        3,
        25,
        10,
        3,
        3,
        10,
        25,
        3,
        5,
        1,
        15,
        4,
        3,
        5,
        3,
        3,
        4,
        20,
        15,
        1,
        15,
        4,
        20,
        4,
        10,
        3,
        10,
        3,
        20,
        4,
        4,
        4,
        30,
        4,
        1,
        2,
        4,
        25,
        4,
        25,
        3,
        31,
        3,
        5,
        5,
        5,
        5,
        25,
        1,
        10,
        2,
        1,
        4,
        4,
        20,
        4,
        2,
        20,
        4,
        10,
        15,
        3,
        3,
        10,
        5,
        15,
        20,
        15,
        1,
        2,
        31,
        20,
        2,
        2,
        3,
        4,
        1,
        2,
        5,
        15,
        20,
        4,
        4,
        2,
        10,
        2,
        1,
        15,
        2,
        1,
        2,
        4,
        25,
        10,
        20,
        3,
        1,
        4,
        4,
        25,
        3,
        10,
        5,
        4,
        1,
        5,
        30,
        4,
        4,
        35,
        4,
        3,
        5,
        3,
        4,
        2,
        10,
        25,
        1,
        20,
        4,
        4,
        4,
        5,
        31,
        10,
        20,
        1,
        2,
        3,
        4,
        2,
        2,
        31,
        3,
        20,
        25,
        10,
        15,
        25,
        3,
        3,
        3,
        1,
        25,
        15,
        10,
        10,
        10,
        20,
        20,
        4,
        4,
        4,
        1,
        15,
        5,
        15,
        5,
        4,
        10,
        25,
        3,
        3,
        3,
        10,
        2,
        4,
        10,
        10,
        1,
        10,
        2,
        5,
        3,
        25,
        10,
        1,
        1,
        10,
        1,
        15,
        2,
        10,
        3,
        4,
        20,
        15,
        10,
        5,
        25,
        10,
        20,
        20,
        4,
        2,
        10,
        1,
        20,
        10,
        15,
        5,
        20,
        4,
        5,
        4,
        5,
        1,
        4,
        3,
        25,
        3,
        4,
        5,
        1,
        10,
        25,
        2,
        1,
        4,
        25,
        3,
        3,
        2,
        25,
        3,
        10,
        1,
        25,
        25,
        4,
        5,
        3,
        3,
        10,
        15,
        2,
        15,
        2,
        10,
        2,
        4,
        4,
        2,
        10,
        5,
        10,
        4,
        15,
        1,
        10,
        5,
        5,
        3,
        4,
        3,
        4,
        20,
        25,
        1,
        3,
        10,
        15,
        20,
        15,
        3,
        15,
        10,
        3,
        10,
        2,
        4,
        1,
        5,
        5,
        15,
        35,
        3,
        2,
        3,
        1,
        3,
        15,
        2,
        15,
        5,
        4,
        1,
        4,
        1,
        1,
        15,
        1,
        1,
        15,
        20,
        10,
        5,
        1,
        4,
        5,
        2,
        5,
        15,
        10,
        5,
        10,
        4,
        20,
        1,
        15,
        1,
        15,
        25,
        2,
        10,
        2,
        15,
        15,
        4,
        25,
        10,
        25,
        30,
        3,
        1,
        4,
        3,
        3,
        30,
        2,
        10,
        2,
        1,
        1,
        10,
        15,
        2,
        2,
        10,
        1,
        2,
        4,
        5,
        5,
        3,
        2,
        20,
        5,
        1,
        3,
        15,
        3,
        5,
        10,
        35,
        5,
        5,
        2,
        15,
        3,
        1,
        2,
        1,
        15,
        1,
        1,
        2,
        30,
        10,
        4,
        4,
        5,
        1,
        2,
        5,
        10,
        20,
        10,
        3,
        15,
        4,
        4,
        15,
        10,
        4,
        5,
        20,
        15,
        35,
        15,
        4,
        2,
        5,
        10,
        5,
        10,
        15,
        3,
        4,
        1,
        20,
        25,
        35,
        2,
        15,
        20,
        15,
        1,
        30,
        2,
        15,
        15,
        1,
        1,
        1,
        2,
        3,
        25,
        3,
        3,
        20,
        5,
        3,
        4,
        4,
        20,
        25,
        15,
        25,
        3,
        4,
        1,
        1,
        5,
        4,
        5,
        20,
        3,
        4,
        10,
        3,
        15,
        15,
        4,
        2,
        10,
        3,
        1,
        15,
        1,
        5,
        35,
        25,
        1,
        5,
        15,
        20,
        20,
        4,
        15,
        2,
        15,
        20,
        1,
        10,
        15,
        20,
        5,
        5,
        10,
        5,
        3,
        5,
        10,
        5,
        5,
        5,
        5,
        5,
        5,
        3,
        1,
        25,
        5,
        1,
        1,
        15,
        2,
        15,
        20,
        15,
        1,
        2,
        30,
        5,
        2,
        5,
        15,
        1,
        2,
        1,
        3,
        3,
        3,
        1,
        25,
        5,
        4,
        3,
        25,
        5,
        1,
        10,
        5,
        15,
        35,
        15,
        1,
        1,
        4,
        20,
        5,
        5,
        3,
        20,
        1,
        1,
        4,
        10,
        10,
        5,
        5,
        10,
        1,
        5,
        1,
        1,
        3,
        20,
        5,
        5,
        3,
        15,
        3,
        3,
        10,
        5,
        20,
        4,
        5,
        10,
        15,
        35,
        3,
        15,
        20,
        10,
        2,
        2,
        10,
        5,
        20,
        20,
        10,
        4
    ],
    "test_pred_y": [
        25,
        10,
        4,
        15,
        1,
        4,
        4,
        4,
        25,
        2,
        4,
        10,
        4,
        1,
        2,
        5,
        25,
        4,
        5,
        15,
        3,
        20,
        2,
        20,
        4,
        35,
        10,
        4,
        4,
        5,
        2,
        5,
        2,
        3,
        15,
        3,
        1,
        5,
        4,
        3,
        10,
        3,
        3,
        3,
        10,
        15,
        4,
        15,
        3,
        3,
        25,
        2,
        4,
        2,
        5,
        5,
        15,
        5,
        15,
        3,
        4,
        10,
        5,
        5,
        3,
        3,
        2,
        4,
        20,
        1,
        20,
        10,
        4,
        4,
        15,
        2,
        4,
        10,
        3,
        3,
        5,
        4,
        5,
        20,
        3,
        1,
        15,
        4,
        25,
        20,
        30,
        10,
        20,
        1,
        2,
        15,
        3,
        3,
        4,
        10,
        25,
        4,
        1,
        4,
        5,
        15,
        31,
        3,
        35,
        25,
        25,
        2,
        1,
        5,
        15,
        2,
        25,
        15,
        1,
        4,
        15,
        4,
        30,
        1,
        1,
        3,
        5,
        1,
        2,
        1,
        3,
        1,
        3,
        4,
        5,
        2,
        20,
        10,
        5,
        3,
        10,
        10,
        1,
        20,
        15,
        5,
        2,
        1,
        2,
        2,
        2,
        20,
        10,
        4,
        4,
        5,
        30,
        2,
        2,
        20,
        15,
        4,
        1,
        4,
        4,
        10,
        5,
        10,
        4,
        1,
        20,
        3,
        20,
        1,
        1,
        1,
        2,
        4,
        3,
        4,
        10,
        3,
        3,
        10,
        15,
        2,
        1,
        10,
        4,
        15,
        25,
        4,
        1,
        10,
        3,
        10,
        25,
        4,
        1,
        4,
        10,
        1,
        10,
        2,
        15,
        3,
        1,
        4,
        20,
        20,
        10,
        5,
        30,
        15,
        1,
        10,
        15,
        4,
        15,
        20,
        3,
        10,
        35,
        2,
        25,
        25,
        10,
        10,
        1,
        2,
        25,
        5,
        10,
        35,
        15,
        10,
        15,
        3,
        5,
        20,
        4,
        15,
        5,
        1,
        20,
        10,
        5,
        10,
        3,
        2,
        25,
        5,
        20,
        15,
        10,
        3,
        25,
        3,
        1,
        20,
        25,
        1,
        4,
        2,
        10,
        3,
        4,
        2,
        5,
        4,
        5,
        5,
        15,
        10,
        4,
        1,
        2,
        15,
        4,
        10,
        1,
        4,
        15,
        5,
        1,
        2,
        3,
        1,
        4,
        4,
        1,
        4,
        1,
        1,
        5,
        1,
        2,
        4,
        20,
        2,
        4,
        2
    ],
    "pipeline_config": {
        "General": {
            "loglevel": "DEBUG",
            "n_jobs": -1,
            "write_figure_to_disk": true,
            "UseCleaner": true,
            "UseStatisticalFeatureSelector": false,
            "UseTransformer": true,
            "UseOutlierRemoval": true,
            "UseContinuousFeatures": false
        },
        "DataPreprocessing": {
            "Cleaning": {
                "DeleteNanColumns": true,
                "DeleteNonfeatures": true,
                "DeleteMissingValues": false,
                "DeleteUndeterminedValue": false,
                "RemoveNaNAmount": true,
                "RemoveNaNAmountArgs": 3,
                "FillNan": true,
                "ShowNan": true
            },
            "OutlierAnalysis": {
                "OutlierRemovalMethod": "ODIN",
                "odinParams": {
                    "k": 30,
                    "T": 0
                },
                "avfParams": {
                    "k": 10
                }
            },
            "Transformer": {
                "Discretization": {
                    "DiscretizeColumns": [
                        "S\u00e5rrand (cm)",
                        "Midte (cm)"
                    ],
                    "DiscretizeMethod": "NONE",
                    "ChiMergeMaximumMergeThreshold": {
                        "S\u00e5rrand (cm)": "inf",
                        "Midte (cm)": "inf"
                    },
                    "DiscretizeDesiredIntervals": {
                        "S\u00e5rrand (cm)": 5,
                        "Midte (cm)": 5
                    }
                },
                "OneHotEncoding": {
                    "UseOneHotEncoding": true,
                    "OneHotEncodeLabels": [
                        "Eksudattype"
                    ]
                },
                "Imputation": {
                    "ImputationMethod": "NONE",
                    "KNN_NearestNeighbors": 5,
                    "KNN_DistanceMetric": "MATRIX"
                },
                "Normalisation": {
                    "NormalisationMethod": "NONE",
                    "NormaliseFeatures": [
                        "Niveau s\u00e5rv\u00e6v",
                        "S\u00e5rskorpe"
                    ]
                }
            },
            "StatisticalFeatureSelection": {
                "score_function": "MUTUAL_INFO_CLASSIFIER",
                "MutualInfoClassifArgs": {
                    "discrete_features": true,
                    "n_neighbors": 3,
                    "random_state": 12
                },
                "GenericUnivariateSelect": true,
                "GenericUnivariateSelectArgs": {
                    "mode": "PERCENTILE",
                    "param": 50
                }
            }
        },
        "ModelSelection": {
            "model": "RANDOM_FOREST",
            "DecisionTree": {
                "criterion": "gini",
                "max_depth": null,
                "min_samples_split": 2,
                "min_samples_leaf": 1,
                "min_weight_fraction_leaf": 0,
                "max_features": "sqrt",
                "random_state": 42,
                "max_leaf_nodes": null,
                "min_impurity_decrease": 0.0,
                "ccp_alpha": 0.0
            },
            "RandomForest": {
                "n_estimators": 100,
                "bootstrap": true,
                "oob_score": false,
                "random_state": 53,
                "max_samples": null
            },
            "CategoricalNaiveBayes": {
                "min_categories": 101
            },
            "NeuralNetwork": {
                "hidden_layer_sizes": [
                    10,
                    10
                ],
                "activation": "tanh",
                "solver": "adam",
                "learning_rate": "adaptive",
                "learning_rate_init": 0.1,
                "batch_size": 2000,
                "alpha": 0.0001,
                "max_iter": 10000,
                "tol": 0.0001,
                "n_iter_no_change": 20,
                "random_state": 678
            }
        },
        "CrossValidationSelection": {
            "cross_validator": "STRATIFIED_KFOLD",
            "StratifiedKFold": {
                "n_splits": 5,
                "shuffle": true,
                "random_state": 177
            }
        },
        "ModelTraining": {
            "training_method": "CROSS_VALIDATION",
            "score_functions": [
                "ALL"
            ],
            "score_function_params": {
                "threshold": 20
            },
            "score_function_weights": {
                "threshold": 0.8,
                "distance": 0.9,
                "exact_accuracy": 1,
                "balanced_accuracy": 1.1
            },
            "train_test_split": {
                "random_state": 111,
                "train_size": 0.8
            },
            "PermutationFeatureImportance": {
                "n_repeats": 1,
                "random_state": 298
            },
            "RFECV": {
                "min_features_to_select": 1,
                "step": 1
            },
            "RandomizedSearchCV": {
                "n_iter": 10,
                "random_state": 378
            },
            "GridSearchCV": {
                "return_train_score": false,
                "refit": "exact_accuracy",
                "verbose": 1
            }
        },
        "ModelEvaluation": {
            "print_model_report": true,
            "plot_confusion_matrix": false,
            "plot_roc_curves": false,
            "plot_feature_importance": false,
            "plot_tree": false,
            "plot_decision_boundary": false
        }
    },
    "grid_config": {
        "ParamGrid": {
            "ParamGridDecisionTree": {
                "criterion": [
                    "gini",
                    "log_loss"
                ],
                "max_depth": {
                    "start": 1,
                    "stop": 25,
                    "step": 5
                },
                "min_samples_split": {
                    "start": 2,
                    "stop": 10,
                    "step": 2
                },
                "min_samples_leaf": {
                    "start": 1,
                    "stop": 10,
                    "step": 2
                },
                "min_weight_fraction_leaf": {
                    "start": 0.0,
                    "stop": 0.5,
                    "step": 0.1
                },
                "max_features": [
                    "sqrt",
                    "log2"
                ],
                "max_leaf_nodes": {
                    "start": 2,
                    "stop": 10,
                    "step": 2
                },
                "min_impurity_decrease": {
                    "start": 0.0,
                    "stop": 0.1,
                    "step": 0.02
                },
                "ccp_alpha": {
                    "start": 0.0,
                    "stop": 0.5,
                    "step": 0.05
                }
            },
            "ParamGridRandomForest": {
                "n_estimators": {
                    "start": 100,
                    "stop": 1000,
                    "step": 100
                },
                "bootstrap": [
                    true
                ],
                "oob_score": [
                    false
                ],
                "max_samples": {
                    "start": 10,
                    "stop": 500,
                    "step": 50
                }
            },
            "ParamGridCategoricalNaiveBayes": {
                "min_categories": [
                    101
                ]
            },
            "ParamGridNeuralNetwork": {
                "hidden_layer_sizes": {
                    "layers": {
                        "start": 2,
                        "stop": 8,
                        "step": 1
                    },
                    "layer_size": [
                        10,
                        15,
                        20,
                        25
                    ]
                },
                "activation": [
                    "logistic",
                    "relu",
                    "tanh"
                ],
                "solver": [
                    "sgd",
                    "adam"
                ],
                "learning_rate": [
                    "adaptive"
                ],
                "learning_rate_init": [
                    0.1
                ],
                "batch_size": [
                    2000
                ],
                "alpha": [
                    0.0001,
                    0.001,
                    0.01,
                    0.1
                ],
                "max_iter": [
                    10000
                ],
                "tol": [
                    0.0001
                ],
                "n_iter_no_change": [
                    20
                ]
            }
        },
        "RandomParamGrid": {
            "RandomParamGridDecisionTree": {
                "criterion": [
                    "gini",
                    "log_loss"
                ],
                "max_depth": {
                    "dist": "RANDINT",
                    "dist_params": {
                        "low": 3,
                        "high": 25,
                        "size": 100
                    }
                },
                "min_samples_split": {
                    "dist": "RANDINT",
                    "dist_params": {
                        "low": 2,
                        "high": 20,
                        "size": 100
                    }
                },
                "min_samples_leaf": {
                    "dist": "RANDINT",
                    "dist_params": {
                        "low": 1,
                        "high": 10,
                        "size": 100
                    }
                },
                "min_weight_fraction_leaf": {
                    "dist": "RANDFLOAT",
                    "dist_params": {
                        "low": 0,
                        "high": 0.5,
                        "size": 100
                    }
                },
                "max_features": [
                    "sqrt",
                    "log2"
                ],
                "max_leaf_nodes": {
                    "dist": "RANDINT",
                    "dist_params": {
                        "low": 2,
                        "high": 10,
                        "size": 100
                    }
                },
                "min_impurity_decrease": {
                    "dist": "RANDFLOAT",
                    "dist_params": {
                        "low": 0.0,
                        "high": 0.1,
                        "size": 100
                    }
                },
                "ccp_alpha": {
                    "dist": "RANDFLOAT",
                    "dist_params": {
                        "low": 0.0,
                        "high": 0.5,
                        "size": 50
                    }
                }
            },
            "RandomParamGridRandomForest": {
                "n_estimators": {
                    "dist": "RANDINT",
                    "dist_params": {
                        "low": 100,
                        "high": 1000,
                        "size": 100
                    }
                },
                "bootstrap": [
                    true
                ],
                "oob_score": [
                    false
                ],
                "max_samples": {
                    "dist": "RANDINT",
                    "dist_params": {
                        "low": 10,
                        "high": 500,
                        "size": 50
                    }
                }
            },
            "RandomParamGridCategoricalNaiveBayes": {
                "min_categories": [
                    101
                ]
            },
            "RandomParamGridNeuralNetwork": {
                "hidden_layer_sizes": {
                    "layers": {
                        "start": 1,
                        "stop": 10,
                        "step": 1
                    },
                    "layer_size": [
                        10,
                        15,
                        20,
                        25
                    ]
                },
                "activation": [
                    "logistic",
                    "relu",
                    "tanh"
                ],
                "solver": [
                    "sgd",
                    "adam"
                ],
                "learning_rate": [
                    "adaptive"
                ],
                "learning_rate_init": [
                    0.1
                ],
                "batch_size": [
                    2000
                ],
                "alpha": [
                    0.0001,
                    0.001,
                    0.01,
                    0.1
                ],
                "max_iter": [
                    10000
                ],
                "tol": [
                    0.0001
                ],
                "n_iter_no_change": [
                    20
                ]
            }
        }
    }
}